mlos_core/__init__.py
mlos_core/data_classes.py
mlos_core/py.typed
mlos_core/util.py
mlos_core/version.py
mlos_core/optimizers/__init__.py
mlos_core/optimizers/flaml_optimizer.py
mlos_core/optimizers/optimizer.py
mlos_core/optimizers/random_optimizer.py
mlos_core/optimizers/bayesian_optimizers/__init__.py
mlos_core/optimizers/bayesian_optimizers/bayesian_optimizer.py
mlos_core/optimizers/bayesian_optimizers/smac_optimizer.py
mlos_core/spaces/__init__.py
mlos_core/spaces/adapters/README.md
mlos_core/spaces/adapters/__init__.py
mlos_core/spaces/adapters/adapter.py
mlos_core/spaces/adapters/identity_adapter.py
mlos_core/spaces/adapters/llamatune.py
mlos_core/spaces/converters/__init__.py
mlos_core/spaces/converters/flaml.py
mlos_core/spaces/converters/util.py
mlos_core-0.6.2.dist-info/METADATA
mlos_core-0.6.2.dist-info/WHEEL
mlos_core-0.6.2.dist-info/top_level.txt
mlos_core-0.6.2.dist-info/RECORD
