Metadata-Version: 2.1
Name: mlos-core
Version: 0.6.2
Summary: MLOS Core Python interface for parameter optimization.
Author-email: Microsoft <mlos-maintainers@service.microsoft.com>
Maintainer-email: Microsoft <mlos-maintainers@service.microsoft.com>
License: MIT
Project-URL: Documentation, https://microsoft.github.io/MLOS/source_tree_docs/mlos_core/
Project-URL: Repository, https://github.com/microsoft/MLOS/
Project-URL: Issues, https://github.com/microsoft/MLOS/issues
Project-URL: Package Source, https://github.com/microsoft/MLOS/tree/main/mlos_core/
Keywords: autotuning,optimization
Classifier: Intended Audience :: Developers
Classifier: Intended Audience :: Science/Research
Classifier: Intended Audience :: System Administrators
Classifier: License :: OSI Approved :: MIT License
Classifier: Operating System :: OS Independent
Classifier: Programming Language :: Python :: 3
Classifier: Programming Language :: Python :: 3.10
Classifier: Programming Language :: Python :: 3.11
Classifier: Programming Language :: Python :: 3.12
Classifier: Programming Language :: Python :: 3.13
Requires-Python: >=3.10
Requires-Dist: scikit-learn>=1.3
Requires-Dist: scipy>=1.3.2
Requires-Dist: numpy>=1.24
Requires-Dist: pandas>=2.2.0; python_version >= "3.9"
Requires-Dist: ConfigSpace>=1.0
Provides-Extra: flaml
Requires-Dist: flaml<2.2.0; extra == "flaml"
Requires-Dist: flaml[blendsearch]; extra == "flaml"
Provides-Extra: smac
Requires-Dist: smac>=2.2.0; extra == "smac"
Provides-Extra: full
Requires-Dist: smac>=2.2.0; extra == "full"
Requires-Dist: flaml<2.2.0; extra == "full"
Requires-Dist: flaml[blendsearch]; extra == "full"
Provides-Extra: full-tests
Requires-Dist: smac>=2.2.0; extra == "full-tests"
Requires-Dist: flaml<2.2.0; extra == "full-tests"
Requires-Dist: flaml[blendsearch]; extra == "full-tests"
Requires-Dist: pytest; extra == "full-tests"
Requires-Dist: pytest-forked; extra == "full-tests"
Requires-Dist: pytest-xdist; extra == "full-tests"
Requires-Dist: pytest-cov; extra == "full-tests"
Requires-Dist: pytest-local-badge; extra == "full-tests"
